{
  "metadata": {
    "version": "1.0",
    "last_update": "2026-04-22 11:12",
    "total_ipos": 53,
    "data_source": "富途牛牛、etnet经济通、新浪财经、智通财经"
  },
  "currently_subscribing": [
    {
      "code": "06810",
      "name": "商米科技-W",
      "name_en": "Sunmi Technology-W",
      "subscription_start": "2026-04-21",
      "subscription_end": "2026-04-24",
      "listing_date": "2026-04-29",
      "price_range": "24.86港元",
      "lot_size": 100,
      "entry_fee": 2511,
      "sponsor": "德意志银行、中信证券、农银国际",
      "cornerstone_investors": "蚂蚁、美团、小米等",
      "cornerstone_score": 9,
      "oversubscription": "待公布",
      "industry": "AI商业物联网",
      "pros": ["全球最大商业物联网提供商", "明星股东背书", "AI+物联网赛道", "全球化布局", "技术壁垒完整"],
      "cons": ["盈利能力待验证(-W)", "市场竞争激烈", "估值偏高", "政策风险"],
      "rating": 7.5,
      "analysis": "商米科技是全球领先的商业物联网（BIoT）解决方案提供商。蚂蚁、美团、小米等战略投资者的加入带来资金和产业协同效应。适合风险偏好较高的成长型投资者。",
      "recommendation": "谨慎推荐，小额参与"
    },
    {
      "code": "01879",
      "name": "曦智科技-P",
      "name_en": "Xizhi Technology-P",
      "subscription_start": "2026-04-20",
      "subscription_end": "2026-04-23",
      "listing_date": "2026-04-28",
      "price_range": "166.60-183.20港元",
      "lot_size": 15,
      "entry_fee": 2776,
      "sponsor": "中金香港、海通国际",
      "cornerstone_investors": "贝莱德、淡马锡、阿里等20家机构",
      "cornerstone_amount": "16.44亿港元",
      "cornerstone_score": 10,
      "oversubscription": "600倍(首日)",
      "industry": "AI硅光芯片",
      "pros": ["技术颠覆性", "明星基石阵容", "市场热度极高", "AI算力赛道", "先发优势"],
      "cons": ["技术商业化不确定", "盈利能力存疑(-P)", "估值极高", "每手股数少", "情绪波动风险"],
      "rating": 8.5,
      "analysis": "曦智科技是全球领先的光电混合算力提供商，硅光芯片是突破摩尔定律限制的重要技术路径。贝莱德、淡马锡等顶级机构的基石投资是对技术实力的强力背书。",
      "recommendation": "强烈推荐参与"
    },
    {
      "code": "02493",
      "name": "迈威生物-B",
      "name_en": "Mabwell Biosciences-B",
      "subscription_start": "2026-04-20",
      "subscription_end": "2026-04-23",
      "listing_date": "2026-04-28",
      "price_range": "27.64-30.71港元",
      "lot_size": 200,
      "entry_fee": 6204,
      "sponsor": "中信证券、海通国际",
      "cornerstone_investors": "君实生物、桂林三金、药明生物等6家",
      "cornerstone_score": 7,
      "oversubscription": "27.76倍(第二日)",
      "industry": "创新药(ADC/TCE)",
      "pros": ["A+H双平台", "已商业化产品", "明星基石投资", "前沿赛道布局", "国际化进展"],
      "cons": ["持续亏损(-B)", "生物类似药竞争", "创新药研发风险", "港股生物医药股分化", "入场费较高"],
      "rating": 6.5,
      "analysis": "迈威生物是一家具备从药物发现至商业化销售端到端能力的创新药企。相比纯研发型公司，已上市产品提供一定安全垫，但创新药研发不确定性较高。",
      "recommendation": "谨慎参与，等待上市后观察"
    }
  ],
  "listing_tomorrow": [
    {
      "code": "03296",
      "name": "华勤技术",
      "name_en": "Huaqin Technology",
      "listing_date": "2026-04-23",
      "pricing": "77.70港元",
      "lot_size": 100,
      "entry_fee": 7770,
      "sponsor": "中金公司、美银证券",
      "cornerstone_investors": "高毅资产等",
      "cornerstone_score": 8,
      "industry": "智能硬件ODM",
      "pros": ["行业龙头地位", "业绩增长迅猛", "数据中心业务爆发", "A+H双平台", "基石投资者强大"],
      "cons": ["毛利率偏低", "客户集中度高", "行业周期性", "竞争加剧", "只能二级市场买入"],
      "rating": 7.0,
      "analysis": "华勤技术是全球领先的智能硬件ODM，数据中心业务受益于AI算力需求爆发。建议上市后观察，如果首日表现平稳可考虑介入。",
      "recommendation": "上市后观察，逢低吸纳"
    }
  ],
  "listed_ipos_2026": [
    {"code": "03030", "name": "南方黄金", "listing_date": "2026-04-21", "ipo_price": null, "grey_market_change": null, "grey_market_pct": null, "grey_market_price": null, "first_day_close": 7.195, "first_day_pct": 50.00, "cumulative_pct": 0.00, "current_pct": 0.62, "market_cap": 55.91},
    {"code": "02476", "name": "胜宏科技", "listing_date": "2026-04-21", "ipo_price": 209.88, "grey_market_change": 126.32, "grey_market_pct": 60.19, "grey_market_price": 336.20, "first_day_close": 336.40, "first_day_pct": 50.09, "cumulative_pct": 60.28, "current_pct": 6.79, "market_cap": 3257.72, "oversubscription": "431倍"},
    {"code": "03277", "name": "长光辰芯", "listing_date": "2026-04-17", "ipo_price": 39.88, "grey_market_change": 28.72, "grey_market_pct": 72.02, "grey_market_price": 68.60, "first_day_close": 86.65, "first_day_pct": 75.53, "cumulative_pct": 117.28, "current_pct": -11.13, "market_cap": 377.18},
    {"code": "00068", "name": "群核科技", "listing_date": "2026-04-17", "ipo_price": 7.62, "grey_market_change": 12.90, "grey_market_pct": 169.29, "grey_market_price": 20.52, "first_day_close": 38.60, "first_day_pct": 144.09, "cumulative_pct": 406.56, "current_pct": -0.52, "market_cap": 657.01, "oversubscription": "1071倍"},
    {"code": "06656", "name": "思格新能", "listing_date": "2026-04-16", "ipo_price": 324.20, "grey_market_change": 273.80, "grey_market_pct": 84.45, "grey_market_price": 598.00, "first_day_close": 545.00, "first_day_pct": 103.42, "cumulative_pct": 68.11, "current_pct": 0.65, "market_cap": 1345.04},
    {"code": "03625", "name": "傅里叶", "listing_date": "2026-03-31", "ipo_price": 40.00, "grey_market_change": 43.50, "grey_market_pct": 108.75, "grey_market_price": 83.50, "first_day_close": 129.00, "first_day_pct": 100.00, "cumulative_pct": 222.50, "current_pct": 2.38, "market_cap": 144.48},
    {"code": "00664", "name": "铜师傅", "listing_date": "2026-03-31", "ipo_price": 60.00, "grey_market_change": -18.04, "grey_market_pct": -30.07, "grey_market_price": 41.96, "first_day_close": 24.44, "first_day_pct": -49.17, "cumulative_pct": -59.27, "current_pct": -1.85, "market_cap": 15.74},
    {"code": "06636", "name": "极视角", "listing_date": "2026-03-30", "ipo_price": 40.00, "grey_market_change": 21.80, "grey_market_pct": 54.50, "grey_market_price": 61.80, "first_day_close": 123.70, "first_day_pct": 150.00, "cumulative_pct": 209.25, "current_pct": 26.48, "market_cap": 139.68},
    {"code": "02726", "name": "瀚天天成", "listing_date": "2026-03-30", "ipo_price": 76.26, "grey_market_change": 28.74, "grey_market_pct": 37.69, "grey_market_price": 105.00, "first_day_close": 108.10, "first_day_pct": 35.06, "cumulative_pct": 41.75, "current_pct": -4.67, "market_cap": 460.06},
    {"code": "02526", "name": "德适-B", "listing_date": "2026-03-30", "ipo_price": 99.00, "grey_market_change": 100.50, "grey_market_pct": 101.52, "grey_market_price": 199.50, "first_day_close": 302.60, "first_day_pct": 111.72, "cumulative_pct": 205.66, "current_pct": 4.92, "market_cap": 268.95},
    {"code": "01021", "name": "华沿机器人", "listing_date": "2026-03-30", "ipo_price": 17.00, "grey_market_change": 1.77, "grey_market_pct": 10.41, "grey_market_price": 18.77, "first_day_close": 23.10, "first_day_pct": 8.24, "cumulative_pct": 35.88, "current_pct": 19.13, "market_cap": 125.57},
    {"code": "02729", "name": "凯乐士科技", "listing_date": "2026-03-24", "ipo_price": 16.66, "grey_market_change": 13.86, "grey_market_pct": 83.19, "grey_market_price": 30.52, "first_day_close": 38.30, "first_day_pct": 84.27, "cumulative_pct": 129.89, "current_pct": -2.10, "market_cap": 163.88},
    {"code": "02632", "name": "泽景股份", "listing_date": "2026-03-24", "ipo_price": 44.20, "grey_market_change": 5.60, "grey_market_pct": 12.67, "grey_market_price": 49.80, "first_day_close": 78.05, "first_day_pct": -36.92, "cumulative_pct": 76.58, "current_pct": -7.08, "market_cap": 96.31},
    {"code": "03355", "name": "飞速创新", "listing_date": "2026-03-23", "ipo_price": 41.60, "grey_market_change": 19.30, "grey_market_pct": 46.39, "grey_market_price": 60.90, "first_day_close": 48.68, "first_day_pct": 13.46, "cumulative_pct": 17.02, "current_pct": 3.57, "market_cap": 194.72},
    {"code": "02701", "name": "国民技术", "listing_date": "2026-03-23", "ipo_price": 10.80, "grey_market_change": 0.90, "grey_market_pct": 8.33, "grey_market_price": 11.70, "first_day_close": 12.39, "first_day_pct": 4.17, "cumulative_pct": 14.72, "current_pct": 3.68, "market_cap": 84.02},
    {"code": "01989", "name": "广合科技", "listing_date": "2026-03-20", "ipo_price": 71.88, "grey_market_change": 23.12, "grey_market_pct": 32.16, "grey_market_price": 95.00, "first_day_close": 147.90, "first_day_pct": 33.56, "cumulative_pct": 105.76, "current_pct": -1.00, "market_cap": 698.79},
    {"code": "03268", "name": "美格智能", "listing_date": "2026-03-10", "ipo_price": 28.86, "grey_market_change": 0.54, "grey_market_pct": 1.87, "grey_market_price": 29.40, "first_day_close": 23.92, "first_day_pct": 1.52, "cumulative_pct": -17.12, "current_pct": -2.05, "market_cap": 72.24},
    {"code": "02715", "name": "埃斯顿", "listing_date": "2026-03-09", "ipo_price": 15.36, "grey_market_change": -1.16, "grey_market_pct": -7.55, "grey_market_price": 14.20, "first_day_close": 12.72, "first_day_pct": -16.02, "cumulative_pct": -17.19, "current_pct": 0.71, "market_cap": 123.10},
    {"code": "02692", "name": "兆威机电", "listing_date": "2026-03-09", "ipo_price": 71.28, "grey_market_change": 12.82, "grey_market_pct": 17.99, "grey_market_price": 84.10, "first_day_close": 65.80, "first_day_pct": 2.41, "cumulative_pct": -7.69, "current_pct": -0.45, "market_cap": 176.00},
    {"code": "02649", "name": "优乐赛共享", "listing_date": "2026-03-09", "ipo_price": 11.00, "grey_market_change": 3.00, "grey_market_pct": 27.27, "grey_market_price": 14.00, "first_day_close": 3.90, "first_day_pct": -43.64, "cumulative_pct": -64.55, "current_pct": 0.00, "market_cap": 3.52},
    {"code": "09981", "name": "沃尔核材", "listing_date": "2026-02-13", "ipo_price": 20.09, "grey_market_change": 0.99, "grey_market_pct": 4.93, "grey_market_price": 21.08, "first_day_close": 20.66, "first_day_pct": 2.94, "cumulative_pct": 2.84, "current_pct": -0.29, "market_cap": 289.22},
    {"code": "02706", "name": "海致科技集团", "listing_date": "2026-02-13", "ipo_price": 27.06, "grey_market_change": 56.94, "grey_market_pct": 210.42, "grey_market_price": 84.00, "first_day_close": 57.05, "first_day_pct": 242.20, "cumulative_pct": 110.83, "current_pct": -5.00, "market_cap": 228.45, "note": "首日涨幅领跑2026 Q1"},
    {"code": "00470", "name": "先导智能", "listing_date": "2026-02-11", "ipo_price": 45.80, "grey_market_change": 0.50, "grey_market_pct": 1.09, "grey_market_price": 46.30, "first_day_close": 57.45, "first_day_pct": 0.00, "cumulative_pct": 25.44, "current_pct": 1.32, "market_cap": 961.84},
    {"code": "02720", "name": "乐欣户外", "listing_date": "2026-02-10", "ipo_price": 12.25, "grey_market_change": 12.23, "grey_market_pct": 99.84, "grey_market_price": 24.48, "first_day_close": 25.76, "first_day_pct": 102.29, "cumulative_pct": 110.29, "current_pct": -0.08, "market_cap": 33.03},
    {"code": "00600", "name": "爱芯元智", "listing_date": "2026-02-10", "ipo_price": 28.20, "grey_market_change": -1.18, "grey_market_pct": -4.18, "grey_market_price": 27.02, "first_day_close": 21.36, "first_day_pct": 0.00, "cumulative_pct": -24.26, "current_pct": -1.39, "market_cap": 125.80},
    {"code": "06809", "name": "澜起科技", "listing_date": "2026-02-09", "ipo_price": 106.89, "grey_market_change": 42.51, "grey_market_pct": 39.77, "grey_market_price": 149.40, "first_day_close": 209.00, "first_day_pct": 63.72, "cumulative_pct": 95.53, "current_pct": 0.87, "market_cap": 2554.40},
    {"code": "03200", "name": "大族数控", "listing_date": "2026-02-06", "ipo_price": 95.80, "grey_market_change": 20.80, "grey_market_pct": 21.71, "grey_market_price": 116.60, "first_day_close": 139.40, "first_day_pct": 14.82, "cumulative_pct": 45.51, "current_pct": -1.69, "market_cap": 674.04},
    {"code": "02714", "name": "牧原股份", "listing_date": "2026-02-06", "ipo_price": 39.00, "grey_market_change": 0.74, "grey_market_pct": 1.90, "grey_market_price": 39.74, "first_day_close": 41.30, "first_day_pct": 3.90, "cumulative_pct": 5.90, "current_pct": -3.14, "market_cap": 2384.25},
    {"code": "02768", "name": "国恩科技", "listing_date": "2026-02-04", "ipo_price": 36.00, "grey_market_change": 13.00, "grey_market_pct": 36.11, "grey_market_price": 49.00, "first_day_close": 51.80, "first_day_pct": 11.56, "cumulative_pct": 43.89, "current_pct": 0.00, "market_cap": 156.05},
    {"code": "09980", "name": "东鹏饮料", "listing_date": "2026-02-03", "ipo_price": 248.00, "grey_market_change": -0.20, "grey_market_pct": -0.08, "grey_market_price": 247.80, "first_day_close": 205.20, "first_day_pct": 1.53, "cumulative_pct": -17.26, "current_pct": -2.29, "market_cap": 1158.91}
  ],
  "statistics": {
    "total_listed": 50,
    "first_day_up": 34,
    "first_day_down": 16,
    "avg_first_day_return": 42.3,
    "best_first_day": {"code": "02706", "name": "海致科技集团", "return": 242.20},
    "worst_first_day": {"code": "00664", "name": "铜师傅", "return": -49.17},
    "highest_grey_market": {"code": "02706", "name": "海致科技集团", "return": 210.42},
    "most_oversubscribed": {"code": "00068", "name": "群核科技", "multiple": 1071}
  },
  "industry_valuation": {
    "AI芯片/算力": {"avg_pe": 45, "avg_pb": 3.2, "note": "高估值反映成长预期"},
    "创新药": {"avg_pe": null, "avg_pb": 2.8, "note": "多数未盈利，看管线价值"},
    "智能硬件ODM": {"avg_pe": 18, "avg_pb": 1.5, "note": "低估值反映代工模式"},
    "商业物联网": {"avg_pe": 32, "avg_pb": 2.1, "note": "新兴赛道，估值分化"},
    "机器人": {"avg_pe": 38, "avg_pb": 2.6, "note": "主题炒作成分高"}
  }
}
